{"moduleName":null,"summaries":[{"symbol":{"__symbol":0,"members":[]},"metadata":{"FORGOTTEN":"FORGOTTEN","HOT":"HOT","NOT_RECALLED":"NOT_RECALLED","PROBLEMATIC":"PROBLEMATIC","RECENTLY_ADDED":"RECENTLY_ADDED"}},{"symbol":{"__symbol":1,"members":[]},"metadata":{"__symbolic":"interface"}},{"symbol":{"__symbol":2,"members":[]},"metadata":{"__symbolic":"interface"}}],"symbols":[{"__symbol":0,"name":"BulkReadCategoriesResponseText","filePath":"./categories.models"},{"__symbol":1,"name":"BulkReadCategoriesResponseEntity","filePath":"./categories.models"},{"__symbol":2,"name":"BulkReadCategoriesResponse","filePath":"./categories.models"}]}